Metadata-Version: 2.1
Name: opal-azure-cli-core
Version: 2.0.70
Summary: Microsoft Azure Command-Line Tools Core Module
Home-page: https://github.com/Azure/azure-cli
Author: Microsoft Corporation
Author-email: azpycli@microsoft.com
License: MIT
Platform: UNKNOWN
Classifier: Development Status :: 5 - Production/Stable
Classifier: Intended Audience :: Developers
Classifier: Intended Audience :: System Administrators
Classifier: Programming Language :: Python
Classifier: Programming Language :: Python :: 2
Classifier: Programming Language :: Python :: 2.7
Classifier: Programming Language :: Python :: 3
Classifier: Programming Language :: Python :: 3.4
Classifier: Programming Language :: Python :: 3.5
Classifier: Programming Language :: Python :: 3.6
Classifier: License :: OSI Approved :: MIT License
Requires-Dist: opal-adal (>=1.2.3)
Requires-Dist: argcomplete (>=1.8.0)
Requires-Dist: opal-azure-cli-telemetry
Requires-Dist: colorama (>=0.3.9)
Requires-Dist: humanfriendly (>=4.7)
Requires-Dist: jmespath
Requires-Dist: knack (~=0.6.2)
Requires-Dist: msrest (>=0.4.4)
Requires-Dist: msrestazure (>=0.4.25)
Requires-Dist: paramiko (<2.5.0,>=2.0.8)
Requires-Dist: pip
Requires-Dist: pygments
Requires-Dist: PyJWT
Requires-Dist: pyopenssl (>=17.1.0)
Requires-Dist: pyyaml
Requires-Dist: requests (>=2.20.0)
Requires-Dist: six
Requires-Dist: tabulate (>=0.7.7)
Requires-Dist: wheel (==0.30.0)
Requires-Dist: azure-mgmt-resource (==2.1.0)
Requires-Dist: pyperclip (>=1.7.0)
Requires-Dist: psutil (>=5.6.1)
Requires-Dist: azure-cli-nspkg (>=2.0.0)
Requires-Dist: futures ; python_version<"3.0"
Requires-Dist: pyopenssl ; python_version<'2.7.9'
Requires-Dist: ndg-httpsclient ; python_version<'2.7.9'
Requires-Dist: pyasn1 ; python_version<'2.7.9'
Requires-Dist: antlr4-python2-runtime ; python_version<'3.0'
Requires-Dist: enum34 ; python_version<'3.4'
Requires-Dist: antlr4-python3-runtime ; python_version>='3.0'
